middle_management/__init__.py
middle_management/apps.py
middle_management/urls.py
middle_management/views.py
middle_management/management/__init__.py
middle_management/management/commands/__init__.py
middle_management/management/commands/noop.py
django_middle_management-0.1.2.dist-info/licenses/LICENSE.txt
django_middle_management-0.1.2.dist-info/WHEEL
django_middle_management-0.1.2.dist-info/METADATA
django_middle_management-0.1.2.dist-info/RECORD
