Metadata-Version: 2.4
Name: django-middle-management
Version: 0.1.2
Summary: A Django app for remote execution of management commands.
Author-email: klove <kennethlove@gmail.com>
Requires-Python: >=3.11
Classifier: Development Status :: 4 - Beta
Classifier: Environment :: Web Environment
Classifier: Framework :: Django
Classifier: Intended Audience :: Developers
Classifier: License :: OSI Approved :: Apache Software License
Classifier: Natural Language :: English
Classifier: Programming Language :: Python
Classifier: Programming Language :: Python :: 3 :: Only
Classifier: Topic :: Internet :: WWW/HTTP
License-File: LICENSE.txt
Requires-Dist: django
Requires-Dist: flit>=3.2
Requires-Dist: interrogate ; extra == "development"
Requires-Dist: ruff ; extra == "development"
Requires-Dist: coverage ; extra == "testing"
Requires-Dist: pytest ; extra == "testing"
Requires-Dist: pytest-cov ; extra == "testing"
Requires-Dist: pytest-django ; extra == "testing"
Requires-Dist: pytest-randomly ; extra == "testing"
Requires-Dist: pytest-xdist ; extra == "testing"
Project-URL: Issues, https://github.com/kennethlove/django-middle-management/issues
Project-URL: Repository, https://github.com/kennethlove/django-middle-management.git
Provides-Extra: development
Provides-Extra: testing
